Workbook

Sheet Dashboard
A1: ❄️ DEBT PAYOFF SNOWBALL TRACKER
A2: Knock out the smallest balance first. Momentum does the rest.
A4: STARTING DEBT | C4: CURRENT BALANCE | E4: PAID OFF | G4: % ELIMINATED
A5: =SUM(Debts!C5:C14) -> 31950 | C5: =SUM(Debts!D5:D14) -> 31950 | E5: =A5-C5 -> 0 | G5: =IF(A5=0,0,E5/A5) -> 0
A8: SNOWBALL ATTACK ORDER
A9: Order | B9: Debt | C9: Current Balance | D9: Min Payment | E9: APR | F9: Status
A10: =Debts!G5 -> 1 | B10: =IF(Debts!B5="","",Debts!B5) -> Store Credit Card | C10: =IF(Debts!B5="","",Debts!D5) -> 850 | D10: =IF(Debts!B5="","",Debts!F5) -> 35 | E10: =IF(Debts!B5="","",Debts!E5) -> 0.22 | F10: =IF(Debts!B5="","",IF(Debts!D5=0,"✓ Paid Off!",IF(Debts!D5<Debts!C5,"🔥 Shrinking","🎯 In Queue"))) -> 🎯 In Queue
A11: =Debts!G6 -> 3 | B11: =IF(Debts!B6="","",Debts!B6) -> Visa Credit Card | C11: =IF(Debts!B6="","",Debts!D6) -> 2400 | D11: =IF(Debts!B6="","",Debts!F6) -> 35 | E11: =IF(Debts!B6="","",Debts!E6) -> 0.22 | F11: =IF(Debts!B6="","",IF(Debts!D6=0,"✓ Paid Off!",IF(Debts!D6<Debts!C6,"🔥 Shrinking","🎯 In Queue"))) -> 🎯 In Queue
A12: =Debts!G7 -> 2 | B12: =IF(Debts!B7="","",Debts!B7) -> Medical Bill | C12: =IF(Debts!B7="","",Debts!D7) -> 1200 | D12: =IF(Debts!B7="","",Debts!F7) -> 35 | E12: =IF(Debts!B7="","",Debts!E7) -> 0.07 | F12: =IF(Debts!B7="","",IF(Debts!D7=0,"✓ Paid Off!",IF(Debts!D7<Debts!C7,"🔥 Shrinking","🎯 In Queue"))) -> 🎯 In Queue
A13: =Debts!G8 -> 4 | B13: =IF(Debts!B8="","",Debts!B8) -> Car Loan | C13: =IF(Debts!B8="","",Debts!D8) -> 9500 | D13: =IF(Debts!B8="","",Debts!F8) -> 150 | E13: =IF(Debts!B8="","",Debts!E8) -> 0.07 | F13: =IF(Debts!B8="","",IF(Debts!D8=0,"✓ Paid Off!",IF(Debts!D8<Debts!C8,"🔥 Shrinking","🎯 In Queue"))) -> 🎯 In Queue
A14: =Debts!G9 -> 5 | B14: =IF(Debts!B9="","",Debts!B9) -> Student Loan | C14: =IF(Debts!B9="","",Debts!D9) -> 18000 | D14: =IF(Debts!B9="","",Debts!F9) -> 150 | E14: =IF(Debts!B9="","",Debts!E9) -> 0.07 | F14: =IF(Debts!B9="","",IF(Debts!D9=0,"✓ Paid Off!",IF(Debts!D9<Debts!C9,"🔥 Shrinking","🎯 In Queue"))) -> 🎯 In Queue
A15: =Debts!G10 | B15: =IF(Debts!B10="","",Debts!B10) | C15: =IF(Debts!B10="","",Debts!D10) | D15: =IF(Debts!B10="","",Debts!F10) | E15: =IF(Debts!B10="","",Debts!E10) | F15: =IF(Debts!B10="","",IF(Debts!D10=0,"✓ Paid Off!",IF(Debts!D10<Debts!C10,"🔥 Shrinking","🎯 In Queue")))
A16: =Debts!G11 | B16: =IF(Debts!B11="","",Debts!B11) | C16: =IF(Debts!B11="","",Debts!D11) | D16: =IF(Debts!B11="","",Debts!F11) | E16: =IF(Debts!B11="","",Debts!E11) | F16: =IF(Debts!B11="","",IF(Debts!D11=0,"✓ Paid Off!",IF(Debts!D11<Debts!C11,"🔥 Shrinking","🎯 In Queue")))
A17: =Debts!G12 | B17: =IF(Debts!B12="","",Debts!B12) | C17: =IF(Debts!B12="","",Debts!D12) | D17: =IF(Debts!B12="","",Debts!F12) | E17: =IF(Debts!B12="","",Debts!E12) | F17: =IF(Debts!B12="","",IF(Debts!D12=0,"✓ Paid Off!",IF(Debts!D12<Debts!C12,"🔥 Shrinking","🎯 In Queue")))
A18: =Debts!G13 | B18: =IF(Debts!B13="","",Debts!B13) | C18: =IF(Debts!B13="","",Debts!D13) | D18: =IF(Debts!B13="","",Debts!F13) | E18: =IF(Debts!B13="","",Debts!E13) | F18: =IF(Debts!B13="","",IF(Debts!D13=0,"✓ Paid Off!",IF(Debts!D13<Debts!C13,"🔥 Shrinking","🎯 In Queue")))
A19: =Debts!G14 | B19: =IF(Debts!B14="","",Debts!B14) | C19: =IF(Debts!B14="","",Debts!D14) | D19: =IF(Debts!B14="","",Debts!F14) | E19: =IF(Debts!B14="","",Debts!E14) | F19: =IF(Debts!B14="","",IF(Debts!D14=0,"✓ Paid Off!",IF(Debts!D14<Debts!C14,"🔥 Shrinking","🎯 In Queue")))
A21: 💡 THE SNOWBALL METHOD
A22: 1. Pay minimums on every debt, every month.
A23: 2. Throw every spare dollar at the smallest balance.
A24: 3. When it dies, roll its entire payment into the next smallest.
A25: 4. Repeat until the last balance hits zero.

Sheet Debts
A1: Debt List — Smallest Balance First Wins
A2: Blue = enter your values | Update Current Balance after each payment — the snowball order re-ranks automatically
A4: # | B4: Debt Name | C4: Starting Balance | D4: Current Balance | E4: APR % | F4: Min Payment | G4: Snowball Order | H4: Notes
A5: 1 | B5: Store Credit Card | C5: 850 | D5: 850 | E5: 0.22 | F5: 35 | G5: =IF($B5="","",IF($D5=0,"✓ PAID OFF",RANK($D5,$D$5:$D$14,1)-COUNTIF($D$5:$D$14,0))) -> 1
A6: 2 | B6: Visa Credit Card | C6: 2400 | D6: 2400 | E6: 0.22 | F6: 35 | G6: =IF($B6="","",IF($D6=0,"✓ PAID OFF",RANK($D6,$D$5:$D$14,1)-COUNTIF($D$5:$D$14,0))) -> 3
A7: 3 | B7: Medical Bill | C7: 1200 | D7: 1200 | E7: 0.07 | F7: 35 | G7: =IF($B7="","",IF($D7=0,"✓ PAID OFF",RANK($D7,$D$5:$D$14,1)-COUNTIF($D$5:$D$14,0))) -> 2
A8: 4 | B8: Car Loan | C8: 9500 | D8: 9500 | E8: 0.07 | F8: 150 | G8: =IF($B8="","",IF($D8=0,"✓ PAID OFF",RANK($D8,$D$5:$D$14,1)-COUNTIF($D$5:$D$14,0))) -> 4
A9: 5 | B9: Student Loan | C9: 18000 | D9: 18000 | E9: 0.07 | F9: 150 | G9: =IF($B9="","",IF($D9=0,"✓ PAID OFF",RANK($D9,$D$5:$D$14,1)-COUNTIF($D$5:$D$14,0))) -> 5
A10: 6 | G10: =IF($B10="","",IF($D10=0,"✓ PAID OFF",RANK($D10,$D$5:$D$14,1)-COUNTIF($D$5:$D$14,0)))
A11: 7 | G11: =IF($B11="","",IF($D11=0,"✓ PAID OFF",RANK($D11,$D$5:$D$14,1)-COUNTIF($D$5:$D$14,0)))
A12: 8 | G12: =IF($B12="","",IF($D12=0,"✓ PAID OFF",RANK($D12,$D$5:$D$14,1)-COUNTIF($D$5:$D$14,0)))
A13: 9 | G13: =IF($B13="","",IF($D13=0,"✓ PAID OFF",RANK($D13,$D$5:$D$14,1)-COUNTIF($D$5:$D$14,0)))
A14: 10 | G14: =IF($B14="","",IF($D14=0,"✓ PAID OFF",RANK($D14,$D$5:$D$14,1)-COUNTIF($D$5:$D$14,0)))
B15: TOTAL | C15: =SUM(C5:C14) -> 31950 | D15: =SUM(D5:D14) -> 31950 | F15: =SUM(F5:F14) -> 405

Sheet Payment Log
A1: Payment Log
A2: Record every payment. Then update the Current Balance on the Debts tab.
A4: # | B4: Date | C4: Debt Name | D4: Amount Paid | E4: Payment Type | F4: Notes
A5: 1
A6: 2
A7: 3
A8: 4
A9: 5
A10: 6
A11: 7
A12: 8
A13: 9
A14: 10
A15: 11
A16: 12
... A104: 100
C105: TOTAL PAID | D105: =SUM(D5:D104) -> 0
