Workbook

Sheet Dashboard
A1: 🛟 EMERGENCY FUND BUILDER
A2: Your safety net, funded one deposit at a time.
A4: TARGET FUND | C4: SAVED SO FAR | E4: STILL TO SAVE | G4: % FUNDED
A5: ='Fund Calculator'!B19 -> 19200 | C5: ='Fund Calculator'!B20 -> 0 | E5: =MAX(0,A5-C5) -> 19200 | G5: =IF(A5=0,0,MIN(1,C5/A5)) -> 0
A8: MILESTONES
A9: Milestone | B9: Amount | C9: Status
A10: Starter fund — $1,000 | B10: =1000 -> 1000 | C10: =IF($C$5>=B10,"✓ Reached!",IF($C$5>=B10*0.5,"⚡ Halfway","🏃 Saving")) -> 🏃 Saving
A11: 1 month of essentials | B11: ='Fund Calculator'!B13 -> 3200 | C11: =IF($C$5>=B11,"✓ Reached!",IF($C$5>=B11*0.5,"⚡ Halfway","🏃 Saving")) -> 🏃 Saving
A12: 3 months of essentials | B12: ='Fund Calculator'!B13*3 -> 9600 | C12: =IF($C$5>=B12,"✓ Reached!",IF($C$5>=B12*0.5,"⚡ Halfway","🏃 Saving")) -> 🏃 Saving
A13: 6 months of essentials | B13: ='Fund Calculator'!B13*6 -> 19200 | C13: =IF($C$5>=B13,"✓ Reached!",IF($C$5>=B13*0.5,"⚡ Halfway","🏃 Saving")) -> 🏃 Saving
A14: Full target | B14: ='Fund Calculator'!B19 -> 19200 | C14: =IF($C$5>=B14,"✓ Reached!",IF($C$5>=B14*0.5,"⚡ Halfway","🏃 Saving")) -> 🏃 Saving
A17: 💡 WHY AN EMERGENCY FUND COMES FIRST
A18: An emergency fund turns a crisis into an inconvenience.
A19: Start with $1,000, then build toward 3–6 months of essentials.
A20: Keep it in a separate high-yield savings account — visible, but not too easy to spend.

Sheet Fund Calculator
A1: Emergency Fund Calculator
A2: Blue = enter your values. Your target = essential monthly costs × months of coverage.
A4: Essential Monthly Expense | B4: Amount | C4: Notes
A5: Housing / Rent | B5: 1400
A6: Utilities | B6: 200
A7: Groceries | B7: 500
A8: Transportation | B8: 300
A9: Insurance | B9: 200
A10: Healthcare | B10: 150
A11: Minimum Debt Payments | B11: 300
A12: Other Essentials | B12: 150
A13: ESSENTIAL MONTHLY TOTAL | B13: =SUM(B5:B12) -> 3200
A15: YOUR PLAN
A16: Months of coverage (3–6 recommended) | B16: 6
A17: Planned monthly contribution | B17: 250
A19: TARGET FUND | B19: =B13*B16 -> 19200
A20: SAVED SO FAR | B20: =SUM('Savings Log'!D5:D104) -> 0
A21: STILL TO SAVE | B21: =MAX(0,B19-B20) -> 19200
A22: MONTHS TO GOAL | B22: =IF(B17<=0,"-",ROUNDUP(B21/B17,0)) -> 77

Sheet Savings Log
A1: Savings Log
A2: Log deposits as positive amounts and withdrawals as negative. Balance runs automatically.
A4: # | B4: Date | C4: Description | D4: Amount (+/-) | E4: Running Balance
A5: 1 | E5: =IF(D5="","",SUM($D$5:D5))
A6: 2 | E6: =IF(D6="","",SUM($D$5:D6))
A7: 3 | E7: =IF(D7="","",SUM($D$5:D7))
A8: 4 | E8: =IF(D8="","",SUM($D$5:D8))
A9: 5 | E9: =IF(D9="","",SUM($D$5:D9))
A10: 6 | E10: =IF(D10="","",SUM($D$5:D10))
A11: 7 | E11: =IF(D11="","",SUM($D$5:D11))
A12: 8 | E12: =IF(D12="","",SUM($D$5:D12))
A13: 9 | E13: =IF(D13="","",SUM($D$5:D13))
A14: 10 | E14: =IF(D14="","",SUM($D$5:D14))
A15: 11 | E15: =IF(D15="","",SUM($D$5:D15))
A16: 12 | E16: =IF(D16="","",SUM($D$5:D16))
... A104: 100 | E104: =IF(D104="","",SUM($D$5:D104))
