Workbook

Sheet Dashboard
A1: 🌱 MONTHLY BUDGET TRACKER
A2: Know where every dollar goes — and make it work harder for you.
A4: MONTHLY INCOME | C4: TOTAL EXPENSES | E4: NET SAVINGS | G4: SAVINGS RATE
A5: =Tracker!C3 -> 5000 | C5: =SUM(Tracker!D7:D21) -> 0 | E5: =A5-C5 -> 5000 | G5: =IF(A5=0,0,E5/A5) -> 1
A8: Category | B8: Budget | C8: Actual | D8: Difference | E8: Status
A9: =Tracker!B7 -> Housing / Rent | B9: =Tracker!C7 -> 1400 | C9: =Tracker!D7 -> 0 | D9: =B9-C9 -> 1400 | E9: =IF(B9=0,"",IF(C9>B9,"⚠ Over Budget",IF(C9/B9>0.9,"⚡ Near Limit","✓ On Track"))) -> ✓ On Track
A10: =Tracker!B8 -> Utilities | B10: =Tracker!C8 -> 200 | C10: =Tracker!D8 -> 0 | D10: =B10-C10 -> 200 | E10: =IF(B10=0,"",IF(C10>B10,"⚠ Over Budget",IF(C10/B10>0.9,"⚡ Near Limit","✓ On Track"))) -> ✓ On Track
A11: =Tracker!B9 -> Groceries | B11: =Tracker!C9 -> 500 | C11: =Tracker!D9 -> 0 | D11: =B11-C11 -> 500 | E11: =IF(B11=0,"",IF(C11>B11,"⚠ Over Budget",IF(C11/B11>0.9,"⚡ Near Limit","✓ On Track"))) -> ✓ On Track
A12: =Tracker!B10 -> Transportation | B12: =Tracker!C10 -> 300 | C12: =Tracker!D10 -> 0 | D12: =B12-C12 -> 300 | E12: =IF(B12=0,"",IF(C12>B12,"⚠ Over Budget",IF(C12/B12>0.9,"⚡ Near Limit","✓ On Track"))) -> ✓ On Track
A13: =Tracker!B11 -> Insurance | B13: =Tracker!C11 -> 200 | C13: =Tracker!D11 -> 0 | D13: =B13-C13 -> 200 | E13: =IF(B13=0,"",IF(C13>B13,"⚠ Over Budget",IF(C13/B13>0.9,"⚡ Near Limit","✓ On Track"))) -> ✓ On Track
A14: =Tracker!B12 -> Healthcare | B14: =Tracker!C12 -> 150 | C14: =Tracker!D12 -> 0 | D14: =B14-C14 -> 150 | E14: =IF(B14=0,"",IF(C14>B14,"⚠ Over Budget",IF(C14/B14>0.9,"⚡ Near Limit","✓ On Track"))) -> ✓ On Track
A15: =Tracker!B13 -> Subscriptions | B15: =Tracker!C13 -> 80 | C15: =Tracker!D13 -> 0 | D15: =B15-C15 -> 80 | E15: =IF(B15=0,"",IF(C15>B15,"⚠ Over Budget",IF(C15/B15>0.9,"⚡ Near Limit","✓ On Track"))) -> ✓ On Track
A16: =Tracker!B14 -> Dining Out | B16: =Tracker!C14 -> 200 | C16: =Tracker!D14 -> 0 | D16: =B16-C16 -> 200 | E16: =IF(B16=0,"",IF(C16>B16,"⚠ Over Budget",IF(C16/B16>0.9,"⚡ Near Limit","✓ On Track"))) -> ✓ On Track
A17: =Tracker!B15 -> Entertainment | B17: =Tracker!C15 -> 100 | C17: =Tracker!D15 -> 0 | D17: =B17-C17 -> 100 | E17: =IF(B17=0,"",IF(C17>B17,"⚠ Over Budget",IF(C17/B17>0.9,"⚡ Near Limit","✓ On Track"))) -> ✓ On Track
A18: =Tracker!B16 -> Clothing | B18: =Tracker!C16 -> 100 | C18: =Tracker!D16 -> 0 | D18: =B18-C18 -> 100 | E18: =IF(B18=0,"",IF(C18>B18,"⚠ Over Budget",IF(C18/B18>0.9,"⚡ Near Limit","✓ On Track"))) -> ✓ On Track
A19: =Tracker!B17 -> Personal Care | B19: =Tracker!C17 -> 80 | C19: =Tracker!D17 -> 0 | D19: =B19-C19 -> 80 | E19: =IF(B19=0,"",IF(C19>B19,"⚠ Over Budget",IF(C19/B19>0.9,"⚡ Near Limit","✓ On Track"))) -> ✓ On Track
A20: =Tracker!B18 -> Savings / Investments | B20: =Tracker!C18 -> 400 | C20: =Tracker!D18 -> 0 | D20: =B20-C20 -> 400 | E20: =IF(B20=0,"",IF(C20>B20,"⚠ Over Budget",IF(C20/B20>0.9,"⚡ Near Limit","✓ On Track"))) -> ✓ On Track
... A23: =Tracker!B21 -> Miscellaneous | B23: =Tracker!C21 -> 90 | C23: =Tracker!D21 -> 0 | D23: =B23-C23 -> 90 | E23: =IF(B23=0,"",IF(C23>B23,"⚠ Over Budget",IF(C23/B23>0.9,"⚡ Near Limit","✓ On Track"))) -> ✓ On Track
A24: TOTAL | B24: =SUM(B9:B23) -> 4200 | C24: =SUM(C9:C23) -> 0 | D24: =SUM(D9:D23) -> 4200

Sheet Tracker
A1: Monthly Budget — Detail Entry
A2: Blue = enter your values | Enter month name in B1 above
A3: INCOME | C3: 5000
A6: # | B6: Category | C6: Budgeted | D6: Actual Spent | E6: Notes
A7: 1 | B7: Housing / Rent | C7: 1400 | D7: 0
A8: 2 | B8: Utilities | C8: 200 | D8: 0
A9: 3 | B9: Groceries | C9: 500 | D9: 0
A10: 4 | B10: Transportation | C10: 300 | D10: 0
A11: 5 | B11: Insurance | C11: 200 | D11: 0
A12: 6 | B12: Healthcare | C12: 150 | D12: 0
A13: 7 | B13: Subscriptions | C13: 80 | D13: 0
A14: 8 | B14: Dining Out | C14: 200 | D14: 0
A15: 9 | B15: Entertainment | C15: 100 | D15: 0
A16: 10 | B16: Clothing | C16: 100 | D16: 0
A17: 11 | B17: Personal Care | C17: 80 | D17: 0
A18: 12 | B18: Savings / Investments | C18: 400 | D18: 0
... A21: 15 | B21: Miscellaneous | C21: 90 | D21: 0
B22: TOTAL | C22: =SUM(C7:C21) -> 4200 | D22: =SUM(D7:D21) -> 0
